tinyrv/__init__.py
tinyrv/common.py
tinyrv/dump.py
tinyrv/fpu.py
tinyrv/opcodes.py
tinyrv/sim.py
tinyrv/system.py
tinyrv/user.py
tinyrv-0.1.0.dist-info/METADATA
tinyrv-0.1.0.dist-info/WHEEL
tinyrv-0.1.0.dist-info/entry_points.txt
tinyrv-0.1.0.dist-info/licenses/LICENSE
tinyrv-0.1.0.dist-info/RECORD
