Metadata-Version: 2.4
Name: tinyrv
Version: 0.1.0
Summary: A tiny RISC-V instruction set simulator
Project-URL: Homepage, https://github.com/s-holst/tinyrv
Project-URL: Issues, https://github.com/s-holst/tinyrv/issues
Author-email: Stefan Holst <mail@s-holst.de>
License-File: LICENSE
Classifier: License :: OSI Approved :: MIT License
Classifier: Operating System :: OS Independent
Classifier: Programming Language :: Python :: 3
Requires-Python: >=3.8
Requires-Dist: dataclasses-struct==1.4.0
Requires-Dist: lief==0.17.0
Requires-Dist: readchar==4.2.1
